minswap/__init__.py
minswap/adapter.py
minswap/constants.py
minswap/pool.py
minswap/types.py
minswap-0.1.1.dist-info/WHEEL
minswap-0.1.1.dist-info/METADATA
minswap-0.1.1.dist-info/RECORD
