Metadata-Version: 2.1
Name: minswap
Version: 0.1.1
Summary: 
Author: Samuel Ostholm
Author-email: kalltrum@gmail.com
Requires-Python: >=3.8,<4.0
Classifier: Programming Language :: Python :: 3
Classifier: Programming Language :: Python :: 3.10
Classifier: Programming Language :: Python :: 3.8
Classifier: Programming Language :: Python :: 3.9
Requires-Dist: blockfrost-python (==0.4.4)
